README.md
setup.cfg
setup.py
catkin_tools_fetch/__init__.py
catkin_tools_fetch/cli.py
catkin_tools_fetch.egg-info/PKG-INFO
catkin_tools_fetch.egg-info/SOURCES.txt
catkin_tools_fetch.egg-info/dependency_links.txt
catkin_tools_fetch.egg-info/entry_points.txt
catkin_tools_fetch.egg-info/requires.txt
catkin_tools_fetch.egg-info/top_level.txt
catkin_tools_fetch/lib/__init__.py
catkin_tools_fetch/lib/dependency_parser.py
catkin_tools_fetch/lib/downloader.py
catkin_tools_fetch/lib/printer.py
catkin_tools_fetch/lib/tools.py
catkin_tools_fetch/lib/update.py