Metadata-Version: 1.2
Name: catkin-tools-fetch
Version: 0.3.4
Summary: A new verb 'dependencies' to manage project dependencies with
Home-page: https://github.com/Photogrammetry-Robotics-Bonn/catkin_tools_fetch
Author: Igor Bogoslavskyi
Author-email: igor.bogoslavskyi@uni-bonn.de
Maintainer: Igor Bogoslavskyi
Maintainer-email: igor.bogoslavskyi@uni-bonn.de
License: Apache 2.0
Download-URL: https://github.com/Photogrammetry-Robotics-Bonn/catkin_tools_fetch/tarball/0.3.4
Keywords: catkin,catkin_tools
Platform: UNKNOWN
Classifier: Environment :: Console
Classifier: Programming Language :: Python
Classifier: Intended Audience :: Developers
Classifier: License :: OSI Approved :: Apache Software License
